ohmyoled/__init__.py
ohmyoled/main.py
ohmyoled/lib/__init__.py
ohmyoled/lib/asynclib.py
ohmyoled/lib/run.py
ohmyoled/lib/tester.py
ohmyoled/lib/sports/__init__.py
ohmyoled/lib/sports/logo.py
ohmyoled/lib/sports/sportbase.py
ohmyoled/lib/sports/sports.py
ohmyoled/lib/sports/apisports/__init__.py
ohmyoled/lib/sports/apisports/apisports.py
ohmyoled/lib/sports/apisports/result.py
ohmyoled/lib/sports/apisports/baseball/__init__.py
ohmyoled/lib/sports/apisports/baseball/baseball.py
ohmyoled/lib/sports/apisports/basketball/__init__.py
ohmyoled/lib/sports/apisports/basketball/basketball.py
ohmyoled/lib/sports/apisports/football/__init__.py
ohmyoled/lib/sports/apisports/football/football.py
ohmyoled/lib/sports/apisports/hockey/__init__.py
ohmyoled/lib/sports/apisports/hockey/hockey.py
ohmyoled/lib/sports/sportsipy/__init__.py
ohmyoled/lib/sports/sportsipy/result.py
ohmyoled/lib/sports/sportsipy/sportsipy.py
ohmyoled/lib/sports/sportsipy/baseball/__init__.py
ohmyoled/lib/sports/sportsipy/baseball/baseball.py
ohmyoled/lib/sports/sportsipy/basketball/__init__.py
ohmyoled/lib/sports/sportsipy/basketball/basketball.py
ohmyoled/lib/sports/sportsipy/football/__init__.py
ohmyoled/lib/sports/sportsipy/football/football.py
ohmyoled/lib/sports/sportsipy/hockey/__init__.py
ohmyoled/lib/sports/sportsipy/hockey/hockey.py
ohmyoled/lib/stock/__init__.py
ohmyoled/lib/stock/stockquote.py
ohmyoled/lib/stock/stocks.py
ohmyoled/lib/upgrade/__init__.py
ohmyoled/lib/upgrade/upgrade.py
ohmyoled/lib/weather/__init__.py
ohmyoled/lib/weather/normal.py
ohmyoled/lib/weather/weather_icon.py
ohmyoled/lib/weather/weatherbase.py
ohmyoled/lib/weather/openweather/__init__.py
ohmyoled/lib/weather/openweather/weather.py
ohmyoled/lib/weather/weathergov/__init__.py
ohmyoled/lib/weather/weathergov/nws.py
ohmyoled/matrix/__init__.py
ohmyoled/matrix/error.py
ohmyoled/matrix/matrix.py
ohmyoled/matrix/terminal.py
ohmyoled/matrix/test.py
ohmyoled/matrix/time.py
ohmyoled/matrix/weathermatrix.py
ohmyoled-2.2.8.dist-info/METADATA
ohmyoled-2.2.8.dist-info/WHEEL
ohmyoled-2.2.8.dist-info/top_level.txt
ohmyoled-2.2.8.dist-info/RECORD
