Metadata-Version: 2.1
Name: ohmyoled
Version: 2.2.8
Summary: 64x32 Oled Matrix Display
Home-page: https://github.com/TheFinalJoke/ohmyoled
Author: thefinaljoke
License: UNKNOWN
Platform: UNKNOWN
Requires-Python: <=3.10.15
Requires-Dist: APScheduler (>=3.10.4)
Requires-Dist: Cython
Requires-Dist: PyInstaller (==6.10.0)
Requires-Dist: RPi.GPIO (==0.7.1)
Requires-Dist: aiohttp
Requires-Dist: dbus-next
Requires-Dist: ephem (==4.1.5)
Requires-Dist: fastjsonschema (>=2.20.0)
Requires-Dist: geocoder (==1.38.1)
Requires-Dist: gpiozero (==2.0.1)
Requires-Dist: ipinfo
Requires-Dist: iso6709
Requires-Dist: lastversion (>=3.5.6)
Requires-Dist: nameparser (==1.1.3)
Requires-Dist: noaa-sdk
Requires-Dist: noaa-sdk (>=0.1.21)
Requires-Dist: numpy
Requires-Dist: pillow (>=10.4.0)
Requires-Dist: printtools (==2.0.1)
Requires-Dist: python-tsl2591 (==0.2.0)
Requires-Dist: questionary (>=2.0.1)
Requires-Dist: regex (>=2020.9.11)
Requires-Dist: sportsipy
Requires-Dist: suntime
Requires-Dist: wget
Requires-Dist: wheel
Provides-Extra: dev
Requires-Dist: pytest (==6.2.5) ; extra == 'dev'
Requires-Dist: twine ; extra == 'dev'
